mongo_to_som/__init__.py
mongo_to_som/mongotosom.py
mongo_to_som-1.0.8.dist-info/METADATA
mongo_to_som-1.0.8.dist-info/WHEEL
mongo_to_som-1.0.8.dist-info/top_level.txt
mongo_to_som-1.0.8.dist-info/RECORD
