Metadata-Version: 2.1
Name: mongo-to-som
Version: 1.0.8
Summary: Library to create Self-Organizing Map from MongoDB collection
Home-page: UNKNOWN
Author: Tomáš Peregrín
Author-email: djtoso@gmail.com
License: MIT
Platform: UNKNOWN
Classifier: Intended Audience :: Developers
Classifier: License :: OSI Approved :: MIT License
Classifier: Programming Language :: Python
Classifier: Programming Language :: Python :: 3
Classifier: Programming Language :: Python :: 3.6
Classifier: Programming Language :: Python :: 3.7
Classifier: Programming Language :: Python :: 3.8
Classifier: Programming Language :: Python :: 3.9
Classifier: Operating System :: OS Independent
Requires-Dist: pandas
Requires-Dist: scikit-learn
Requires-Dist: pymongo
Requires-Dist: numpy
Requires-Dist: scipy
Requires-Dist: matplotlib
